{
  "type": "FeatureCollection",
  "features": [
    {
      "type": "Feature",
      "properties": {
        "id": "DT-001",
        "zone": "C-1",
        "district": "downtown",
        "height": 45,
        "width": 120,
        "depth": 100,
        "description": "Downtown mixed-use development — ideal for retail/office",
        "status": "Available",
        "roi": "22-28%"
      },
      "geometry": {"type": "Point", "coordinates": [-97.3936, 37.6444]}
    },
    {
      "type": "Feature",
      "properties": {
        "id": "SI-001",
        "zone": "I-1",
        "district": "south",
        "height": 65,
        "width": 250,
        "depth": 180,
        "description": "South industrial corridor — logistics & manufacturing hub",
        "status": "Available",
        "roi": "18-24%"
      },
      "geometry": {"type": "Point", "coordinates": [-97.3820, 37.6250]}
    },
    {
      "type": "Feature",
      "properties": {
        "id": "NG-001",
        "zone": "R-1",
        "district": "north",
        "height": 35,
        "width": 150,
        "depth": 120,
        "description": "North gateway residential — multi-family opportunity",
        "status": "Available",
        "roi": "16-20%"
      },
      "geometry": {"type": "Point", "coordinates": [-97.3980, 37.6600]}
    },
    {
      "type": "Feature",
      "properties": {
        "id": "LS-001",
        "zone": "PUD",
        "district": "lakeside",
        "height": 55,
        "width": 180,
        "depth": 140,
        "description": "Lakeside recreation & mixed-use — high-value amenity zone",
        "status": "Available",
        "roi": "24-30%"
      },
      "geometry": {"type": "Point", "coordinates": [-97.4050, 37.6350]}
    },
    {
      "type": "Feature",
      "properties": {
        "id": "DT-002",
        "zone": "C-1",
        "district": "downtown",
        "height": 50,
        "width": 100,
        "depth": 90,
        "description": "Downtown office/retail secondary site",
        "status": "Available",
        "roi": "20-25%"
      },
      "geometry": {"type": "Point", "coordinates": [-97.3920, 37.6460]}
    },
    {
      "type": "Feature",
      "properties": {
        "id": "SI-002",
        "zone": "I-1",
        "district": "south",
        "height": 70,
        "width": 300,
        "depth": 200,
        "description": "South industrial expansion — major distribution facility",
        "status": "Available",
        "roi": "19-25%"
      },
      "geometry": {"type": "Point", "coordinates": [-97.3750, 37.6200]}
    },
    {
      "type": "Feature",
      "properties": {
        "id": "NG-002",
        "zone": "R-1",
        "district": "north",
        "height": 40,
        "width": 160,
        "depth": 130,
        "description": "North gateway secondary residential",
        "status": "Available",
        "roi": "17-21%"
      },
      "geometry": {"type": "Point", "coordinates": [-97.3990, 37.6620]}
    }
  ]
}
